transcendent/__init__.py
transcendent/calibrate_rf_knn.py
transcendent/calibration.py
transcendent/classifiers/__init__.py
transcendent/classifiers/lightgbm_margin.py
transcendent/classifiers/lightgbm_p.py
transcendent/classifiers/ncm_classifier.py
transcendent/classifiers/random_forest.py
transcendent/classifiers/random_forest_p.py
transcendent/data.py
transcendent/scores.py
transcendent/thresholding.py
transcendent/utils.py
transcendent_multiclass_cdd_wdis-1.1.1.dist-info/LICENSE
transcendent_multiclass_cdd_wdis-1.1.1.dist-info/METADATA
transcendent_multiclass_cdd_wdis-1.1.1.dist-info/WHEEL
transcendent_multiclass_cdd_wdis-1.1.1.dist-info/RECORD
