Metadata-Version: 2.3
Name: transcendent-multiclass-CDD__Wdis
Version: 1.1.1
Summary: Transcendent adaptation for multiclass problems
License: BSD 3-Clause License
Author: Luca Fabri
Author-email: luca.fabri1999@gmail.com
Requires-Python: >=3.10,<4.0
Classifier: License :: Other/Proprietary License
Classifier: Programming Language :: Python :: 3
Classifier: Programming Language :: Python :: 3.10
Classifier: Programming Language :: Python :: 3.11
Classifier: Programming Language :: Python :: 3.12
Classifier: Programming Language :: Python :: 3.13
Requires-Dist: contourpy (==1.3.2)
Requires-Dist: coverage (>=7.8.0,<8.0.0)
Requires-Dist: cycler (==0.12.1)
Requires-Dist: fonttools (==4.58.0)
Requires-Dist: joblib (==1.5.0)
Requires-Dist: kiwisolver (==1.4.8)
Requires-Dist: lightgbm (>=4.6.0,<5.0.0)
Requires-Dist: matplotlib (==3.10.3)
Requires-Dist: mypy (>=1.15.0,<2.0.0)
Requires-Dist: numpy (==2.2.5)
Requires-Dist: packaging (==25.0)
Requires-Dist: pandas (==2.2.3)
Requires-Dist: pillow (==11.2.1)
Requires-Dist: pyparsing (==3.2.3)
Requires-Dist: pytest (>=8.3.5,<9.0.0)
Requires-Dist: python-dateutil (==2.9.0.post0)
Requires-Dist: pytz (==2025.2)
Requires-Dist: ruff (>=0.11.6,<0.12.0)
Requires-Dist: scikit-learn (==1.6.1)
Requires-Dist: scipy (==1.15.3)
Requires-Dist: seaborn (==0.13.2)
Requires-Dist: six (==1.17.0)
Requires-Dist: termcolor (==3.1.0)
Requires-Dist: tesseract (==0.1.3)
Requires-Dist: threadpoolctl (==3.6.0)
Requires-Dist: tqdm (==4.67.1)
Requires-Dist: tzdata (==2025.2)
Requires-Dist: ujson (==5.10.0)
Requires-Dist: xgboost (>=3.0.1,<4.0.0)
